[{"day 1": [{"meal_name": "breakfast", "meal_time": "9:00", "beverage": "20", "main_course": "6"}, {"meal_name": "lunch", "meal_time": "13:00", "beverage": "10", "main_course": "11", "side": "21"}, {"meal_name": "dinner", "meal_time": "20:00", "beverage": "3", "main_course": "9", "dessert": "25", "side": "2"}]}, {"day 2": [{"meal_name": "breakfast", "meal_time": "9:00", "beverage": "21", "main_course": "24"}, {"meal_name": "lunch", "meal_time": "13:00", "beverage": "8", "main_course": "17", "side": "10"}, {"meal_name": "dinner", "meal_time": "20:00", "beverage": "9", "main_course": "22", "dessert": "8", "side": "15"}]}, {"day 3": [{"meal_name": "breakfast", "meal_time": "9:00", "beverage": "25", "main_course": "2"}, {"meal_name": "lunch", "meal_time": "13:00", "beverage": "25", "main_course": "17", "side": "12"}, {"meal_name": "dinner", "meal_time": "20:00", "beverage": "20", "main_course": "23", "dessert": "24", "side": "22"}]}]